CONTRIBUTING.md
Jenkinsfile
MANIFEST.in
README.rst
setup.cfg
setup.py
buildouts/plone4/buildout.cfg
buildouts/plone4/install.sh
buildouts/plone4/versions.cfg
docs/HISTORY.txt
docs/INSTALL.txt
docs/LICENSE.GPL
docs/LICENSE.txt
eea/__init__.py
eea.downloads.egg-info/PKG-INFO
eea.downloads.egg-info/SOURCES.txt
eea.downloads.egg-info/dependency_links.txt
eea.downloads.egg-info/entry_points.txt
eea.downloads.egg-info/namespace_packages.txt
eea.downloads.egg-info/not-zip-safe
eea.downloads.egg-info/requires.txt
eea.downloads.egg-info/top_level.txt
eea/downloads/README.txt
eea/downloads/__init__.py
eea/downloads/config.py
eea/downloads/configure.zcml
eea/downloads/interfaces.py
eea/downloads/patch.py
eea/downloads/patches.zcml
eea/downloads/profiles.zcml
eea/downloads/setuphandlers.py
eea/downloads/version.txt
eea/downloads/Extensions/install.py
eea/downloads/content/DirectoryView.py
eea/downloads/content/__init__.py
eea/downloads/profiles/default/eea.downloads.txt
eea/downloads/profiles/default/metadata.xml
eea/downloads/profiles/uninstall/eea.downloads.uninstall.txt
eea/downloads/storage/__init__.py
eea/downloads/storage/configure.zcml
eea/downloads/storage/handler.py
eea/downloads/storage/interfaces.py
eea/downloads/tests/__init__.py
eea/downloads/tests/base.py
eea/downloads/tests/test_doctest.py
eea/downloads/upgrades/__init__.py
eea/downloads/upgrades/configure.zcml