Metadata-Version: 1.1
Name: eea.downloads
Version: 2.0
Summary: EEA Downloads Media Storage
Home-page: https://github.com/collective/eea.downloads
Author: European Environment Agency: IDM2 A-Team
Author-email: eea-edw-a-team-alerts@googlegroups.com
License: GPL version 2
Keywords: EEA Add-ons Plone Zope
Platform: UNKNOWN
Classifier: Framework :: Zope2
Classifier: Framework :: Plone
Classifier: Framework :: Plone :: 4.0
Classifier: Framework :: Plone :: 4.1
Classifier: Framework :: Plone :: 4.2
Classifier: Framework :: Plone :: 4.3
Classifier: Programming Language :: Zope
Classifier: Programming Language :: Python
Classifier: Programming Language :: Python :: 2.7
Classifier: Topic :: Software Development :: Libraries :: Python Modules
Classifier: License :: OSI Approved :: GNU General Public License (GPL)
